lintipy.py
lintipy-1.4.4.dist-info/LICENSE
lintipy-1.4.4.dist-info/METADATA
lintipy-1.4.4.dist-info/WHEEL
lintipy-1.4.4.dist-info/top_level.txt
lintipy-1.4.4.dist-info/RECORD
