Metadata-Version: 2.1
Name: lintipy
Version: 1.4.4
Summary: Run python based static file linters on AWS lambda.
Home-page: https://github.com/lambda-lint/lintipy
Author: Johannes Hoppe
Author-email: info@johanneshoppe.com
License: Apache-2
Keywords: linter,lambda,aws,amazon
Platform: UNKNOWN
Classifier: Development Status :: 4 - Beta
Classifier: Environment :: Console
Classifier: Intended Audience :: Developers
Classifier: Intended Audience :: Information Technology
Classifier: License :: OSI Approved :: Apache Software License
Classifier: Operating System :: OS Independent
Classifier: Programming Language :: Python
Requires-Dist: cryptography
Requires-Dist: PyJWT (>=2.0.0)
Requires-Dist: requests
